typekeeper/__init__.py
typekeeper/typekeeper.py
typekeeper-0.0.2.dist-info/METADATA
typekeeper-0.0.2.dist-info/WHEEL
typekeeper-0.0.2.dist-info/top_level.txt
typekeeper-0.0.2.dist-info/RECORD
