Metadata-Version: 2.4
Name: typekeeper
Version: 0.0.2
Summary: An extensive drop-in argument validator.
Home-page: https://www.github.com/PrivatePandaCO/typekeeper
Author: Parth Mittal
Author-email: parth@privatepanda.co
License: MIT
Project-URL: Documentation, https://github.com/PrivatePandaCO/typekeeper/blob/master/README.md
Project-URL: Github, https://github.com/PrivatePandaCO/typekeeper
Classifier: Programming Language :: Python :: 3
Classifier: License :: OSI Approved :: MIT License
Classifier: Operating System :: OS Independent
Requires-Python: >=3.9
Dynamic: author
Dynamic: author-email
Dynamic: classifier
Dynamic: description
Dynamic: description-content-type
Dynamic: home-page
Dynamic: license
Dynamic: project-url
Dynamic: requires-python
Dynamic: summary
